aquami/Instruction manual.pdf
aquami/__init__.py
aquami/autoSelect.py
aquami/display.py
aquami/gui.py
aquami/icon.ico
aquami/inout.py
aquami/measure.py
aquami/segment.py
aquami/tkSimpleDialog.py
aquami/micrographs/Sample.tif
aquami/ttps/mes_area.txt
aquami/ttps/mes_area_fraction.txt
aquami/ttps/mes_connected_length.txt
aquami/ttps/mes_diameter.txt
aquami/ttps/mes_length.txt
aquami/ttps/opt_output_excel.txt
aquami/ttps/opt_save_binary.txt
aquami/ttps/opt_save_movie.txt
aquami/ttps/opt_save_pdf.txt
aquami/ttps/opt_show_steps.txt
aquami/ttps/seg_accurate.txt
aquami/ttps/seg_binary.txt
aquami/ttps/seg_fast.txt
aquami/ttps/seg_manual.txt
aquami-1.1.0.dist-info/METADATA
aquami-1.1.0.dist-info/RECORD
aquami-1.1.0.dist-info/WHEEL
aquami-1.1.0.dist-info/top_level.txt
