Metadata-Version: 2.1
Name: aquami
Version: 1.1.0
Summary: A module to extract quantitative microstructure information from micrographs of morphologically complex microstructures.
Home-page: https://github.com/JStuckner/aquami
Author: Joshua Stuckner
Author-email: stuckner@vt.edu
License: MIT
Platform: UNKNOWN
Requires-Python: >=3
Requires-Dist: matplotlib (>=1.5.3)
Requires-Dist: numpy (>=1.12.0)
Requires-Dist: openpyxl (>=2.3.2)
Requires-Dist: pandas (>=0.18.1)
Requires-Dist: scipy (>=0.18.1)
Requires-Dist: scikit-image (>=0.12.3)
Requires-Dist: Pillow (>=4.0.0)
Requires-Dist: setuptools (>=34.3.2)
